{
    "PATIENT_VISIT": {
        "elements": [
            {
                "segment": "PV1",
                "minOccurs": "1",
                "maxOccurs": "1"
            },
            {
                "segment": "PV2",
                "minOccurs": "0",
                "maxOccurs": "1"
            }
        ]
    },
    "INSURANCE": {
        "elements": [
            {
                "segment": "IN1",
                "minOccurs": "1",
                "maxOccurs": "1"
            },
            {
                "segment": "IN2",
                "minOccurs": "0",
                "maxOccurs": "1"
            },
            {
                "segment": "IN3",
                "minOccurs": "0",
                "maxOccurs": "1"
            }
        ]
    },
    "PATIENT": {
        "elements": [
            {
                "segment": "PID",
                "minOccurs": "1",
                "maxOccurs": "1"
            },
            {
                "segment": "PD1",
                "minOccurs": "0",
                "maxOccurs": "1"
            },
            {
                "segment": "NTE",
                "minOccurs": "0",
                "maxOccurs": "unbounded"
            },
            {
                "segment": "NK1",
                "minOccurs": "0",
                "maxOccurs": "unbounded"
            },
            {
                "group": "PATIENT_VISIT",
                "minOccurs": "0",
                "maxOccurs": "1"
            },
            {
                "group": "INSURANCE",
                "minOccurs": "0",
                "maxOccurs": "unbounded"
            },
            {
                "segment": "GT1",
                "minOccurs": "0",
                "maxOccurs": "1"
            },
            {
                "segment": "AL1",
                "minOccurs": "0",
                "maxOccurs": "unbounded"
            }
        ]
    },
    "TIMING": {
        "elements": [
            {
                "segment": "TQ1",
                "minOccurs": "1",
                "maxOccurs": "1"
            },
            {
                "segment": "TQ2",
                "minOccurs": "0",
                "maxOccurs": "unbounded"
            }
        ]
    },
    "OBSERVATION": {
        "elements": [
            {
                "segment": "OBX",
                "minOccurs": "1",
                "maxOccurs": "1"
            },
            {
                "segment": "NTE",
                "minOccurs": "0",
                "maxOccurs": "unbounded"
            }
        ]
    },
    "CONTAINER": {
        "elements": [
            {
                "segment": "SAC",
                "minOccurs": "1",
                "maxOccurs": "1"
            },
            {
                "segment": "OBX",
                "minOccurs": "0",
                "maxOccurs": "unbounded"
            }
        ]
    },
    "SPECIMEN": {
        "elements": [
            {
                "segment": "SPM",
                "minOccurs": "1",
                "maxOccurs": "1"
            },
            {
                "segment": "OBX",
                "minOccurs": "0",
                "maxOccurs": "unbounded"
            },
            {
                "group": "CONTAINER",
                "minOccurs": "0",
                "maxOccurs": "unbounded"
            }
        ]
    },
    "PATIENT_PRIOR": {
        "elements": [
            {
                "segment": "PID",
                "minOccurs": "1",
                "maxOccurs": "1"
            },
            {
                "segment": "PD1",
                "minOccurs": "0",
                "maxOccurs": "1"
            }
        ]
    },
    "PATIENT_VISIT_PRIOR": {
        "elements": [
            {
                "segment": "PV1",
                "minOccurs": "1",
                "maxOccurs": "1"
            },
            {
                "segment": "PV2",
                "minOccurs": "0",
                "maxOccurs": "1"
            }
        ]
    },
    "TIMING_PRIOR": {
        "elements": [
            {
                "segment": "TQ1",
                "minOccurs": "1",
                "maxOccurs": "1"
            },
            {
                "segment": "TQ2",
                "minOccurs": "0",
                "maxOccurs": "unbounded"
            }
        ]
    },
    "OBSERVATION_PRIOR": {
        "elements": [
            {
                "segment": "OBX",
                "minOccurs": "1",
                "maxOccurs": "1"
            },
            {
                "segment": "NTE",
                "minOccurs": "0",
                "maxOccurs": "unbounded"
            }
        ]
    },
    "ORDER_PRIOR": {
        "elements": [
            {
                "segment": "ORC",
                "minOccurs": "0",
                "maxOccurs": "1"
            },
            {
                "segment": "OBR",
                "minOccurs": "1",
                "maxOccurs": "1"
            },
            {
                "group": "TIMING_PRIOR",
                "minOccurs": "0",
                "maxOccurs": "unbounded"
            },
            {
                "segment": "NTE",
                "minOccurs": "0",
                "maxOccurs": "unbounded"
            },
            {
                "segment": "CTD",
                "minOccurs": "0",
                "maxOccurs": "1"
            },
            {
                "group": "OBSERVATION_PRIOR",
                "minOccurs": "1",
                "maxOccurs": "unbounded"
            }
        ]
    },
    "PRIOR_RESULT": {
        "elements": [
            {
                "group": "PATIENT_PRIOR",
                "minOccurs": "0",
                "maxOccurs": "1"
            },
            {
                "group": "PATIENT_VISIT_PRIOR",
                "minOccurs": "0",
                "maxOccurs": "1"
            },
            {
                "segment": "AL1",
                "minOccurs": "0",
                "maxOccurs": "unbounded"
            },
            {
                "group": "ORDER_PRIOR",
                "minOccurs": "1",
                "maxOccurs": "unbounded"
            }
        ]
    },
    "ORDER": {
        "elements": [
            {
                "segment": "ORC",
                "minOccurs": "1",
                "maxOccurs": "1"
            },
            {
                "group": "TIMING",
                "minOccurs": "0",
                "maxOccurs": "unbounded"
            },
            {
                "segment": "OBR",
                "minOccurs": "1",
                "maxOccurs": "1"
            },
            {
                "segment": "NTE",
                "minOccurs": "0",
                "maxOccurs": "unbounded"
            },
            {
                "segment": "CTD",
                "minOccurs": "0",
                "maxOccurs": "1"
            },
            {
                "segment": "DG1",
                "minOccurs": "0",
                "maxOccurs": "unbounded"
            },
            {
                "group": "OBSERVATION",
                "minOccurs": "0",
                "maxOccurs": "unbounded"
            },
            {
                "group": "SPECIMEN",
                "minOccurs": "0",
                "maxOccurs": "unbounded"
            },
            {
                "group": "PRIOR_RESULT",
                "minOccurs": "0",
                "maxOccurs": "unbounded"
            },
            {
                "segment": "FT1",
                "minOccurs": "0",
                "maxOccurs": "unbounded"
            },
            {
                "segment": "CTI",
                "minOccurs": "0",
                "maxOccurs": "unbounded"
            },
            {
                "segment": "BLG",
                "minOccurs": "0",
                "maxOccurs": "1"
            }
        ]
    },
    "OMG_O19": {
        "elements": [
            {
                "segment": "MSH",
                "minOccurs": "1",
                "maxOccurs": "1"
            },
            {
                "segment": "SFT",
                "minOccurs": "0",
                "maxOccurs": "unbounded"
            },
            {
                "segment": "NTE",
                "minOccurs": "0",
                "maxOccurs": "unbounded"
            },
            {
                "group": "PATIENT",
                "minOccurs": "0",
                "maxOccurs": "1"
            },
            {
                "group": "ORDER",
                "minOccurs": "1",
                "maxOccurs": "unbounded"
            }
        ]
    }
}